cz_git_repo_jira_conventional.py
cz_git_repo_jira_conventional-2.0.1.dist-info/LICENSE
cz_git_repo_jira_conventional-2.0.1.dist-info/METADATA
cz_git_repo_jira_conventional-2.0.1.dist-info/WHEEL
cz_git_repo_jira_conventional-2.0.1.dist-info/entry_points.txt
cz_git_repo_jira_conventional-2.0.1.dist-info/top_level.txt
cz_git_repo_jira_conventional-2.0.1.dist-info/RECORD
