Metadata-Version: 2.1
Name: cz-git-repo-jira-conventional
Version: 2.0.1
Summary: Extend the commitizen tools to create conventional commits and README that link to Jira and Git repo.
Home-page: https://github.com/wisnerjr/cz-git-repo-jira-conventional/
Author: Wisner Júnior
Author-email: wisner@gmail.com
License: MIT
License-File: LICENSE
Requires-Dist: commitizen
